statgrit/__init__.py
statgrit/sg.py
StatGrit-0.1.1.dist-info/METADATA
StatGrit-0.1.1.dist-info/WHEEL
StatGrit-0.1.1.dist-info/top_level.txt
StatGrit-0.1.1.dist-info/RECORD
