Metadata-Version: 2.1
Name: StatGrit
Version: 0.1.1
Summary: This a custom module for tracking local game scores which are modfied manually.
Home-page: https://github.com/NINJAGAMING107/statgrit
Author: Sidharth (NINJA)
Author-email: sidharthsnair357@gmail.com
Classifier: Programming Language :: Python :: 3
Classifier: License :: OSI Approved :: MIT License
Classifier: Operating System :: OS Independent
Requires-Python: >=3.6
